yta_programming_path/__init__.py
yta_programming_path-0.0.2.dist-info/licenses/LICENSE
yta_programming_path-0.0.2.dist-info/METADATA
yta_programming_path-0.0.2.dist-info/WHEEL
yta_programming_path-0.0.2.dist-info/RECORD
