Metadata-Version: 2.4
Name: yta-programming-path
Version: 0.0.2
Summary: Youtube Autonomous Programming Path Module
License-File: LICENSE
Author: danialcala94
Author-email: danielalcalavalera@gmail.com
Requires-Python: ==3.9
Classifier: Programming Language :: Python :: 3
Classifier: Programming Language :: Python :: 3.9
Requires-Dist: yta_file (>=0.0.1,<1.0.0)
